tls_client/__init__.py
tls_client/adapters.py
tls_client/cffi.py
tls_client/config.py
tls_client/dependencies/__init__.py
tls_client/dependencies/tls-client-32.dll
tls_client/dependencies/tls-client-64.dll
tls_client/dependencies/tls-client-amd64.so
tls_client/dependencies/tls-client-arm64.dylib
tls_client/dependencies/tls-client-arm64.so
tls_client/dependencies/tls-client-x86.dylib
tls_client/dependencies/tls-client-x86.so
tls_client/exceptions.py
tls_client/sessions.py
tls_client/settings.py
tls_client3-1.1.2.dist-info/LICENSE
tls_client3-1.1.2.dist-info/METADATA
tls_client3-1.1.2.dist-info/WHEEL
tls_client3-1.1.2.dist-info/RECORD
