Metadata-Version: 2.3
Name: tls-client3
Version: 1.1.2
Summary: Advanced Python HTTP Client.
License: MIT
Author: Florian Zager
Author-email: florian@zager-online.de
Requires-Python: >=3.11,<4.0
Classifier: Environment :: Web Environment
Classifier: Intended Audience :: Developers
Classifier: License :: OSI Approved :: MIT License
Classifier: Natural Language :: English
Classifier: Operating System :: MacOS :: MacOS X
Classifier: Operating System :: Microsoft :: Windows
Classifier: Operating System :: Unix
Classifier: Programming Language :: Python
Classifier: Programming Language :: Python :: 3
Classifier: Programming Language :: Python :: 3.11
Classifier: Programming Language :: Python :: 3.12
Classifier: Programming Language :: Python :: 3.13
Classifier: Topic :: Internet :: WWW/HTTP
Classifier: Topic :: Software Development :: Libraries
Requires-Dist: requests (>=2.32.3,<3.0.0)
Requires-Dist: typing-extensions (>=4.13.0,<5.0.0)
Requires-Dist: urllib3 (>=2.3.0,<3.0.0)
Project-URL: Repository, https://github.com/JTJag/python-tls-client
